	<item>
		<title>HOSTILES</title>
		<microhd>ed5285a1ae6c365f914215493a18bb43c0fd814b</microhd>
		<fullhd>NA</fullhd>
		<tresd>NA</tresd>
		<cuatrok>NA</cuatrok>
		<thumbnail>https://image.tmdb.org/t/p/original/6FxhTzubzDdFE6ZyzbxgTwIyx7l.jpg</thumbnail>
		<fanart>https://image.tmdb.org/t/p/original/vBSsIyWExRpe3Robi8SAnayrMq1.jpg</fanart>
		<date>2017</date>
		<genre>Western. Drama</genre>
		<extra>NA</extra>
		<info>El legendario capitán del ejército, Joseph J. Blocker (Christian Bale), se ve en la obligación de acompañar a un moribundo jefe cheyenne (Wes Studi), y a su familia, de regreso a las tierras de su tribu. Para ello tendrán que emprender un peligroso viaje por las praderas montañosas de Nuevo México, dónde se encontrarán con una joven viuda (Rosamund Pike) cuya familia fue asesinada en las llanuras por un grupo de comanches que aún rondan por la zona. Juntos tendrán que unir fuerzas para sobrevivir al castigador paisaje y a las hostiles tribus comanche que se encuentran por el camino.</info>
	</item>
	<item>
		<title>LA MISION (11416)</title>
		<microhd>NA</microhd>
		<fullhd>95075b4ce991e1774722e06a0f26d03c34770e6d</fullhd>
		<tresd>NA</tresd>
		<cuatrok>NA</cuatrok>
		<thumbnail>https://image.tmdb.org/t/p/original/rubwmohm8t5TTtBZyYQ9BHOwDUQ.jpg</thumbnail>
		<fanart>https://image.tmdb.org/t/p/original/v0Z8jCtlsDEGrr90Gpcz7n7oun0.jpg</fanart>
		<date>1986</date>
		<genre>Aventura. Drama. Acción. Historia</genre>
		<extra>NA</extra>
		<info>Siglo XVIII. Los grandes imperios colonialistas, España y Portugal, se disputan el dominio de Ámerica del Sur. El padre Gabriel dirige una misión en lo alto de las montañas de Brasil, donde los nativos son evangelizados y llevan una vida pacífica. Hasta allí llega Mendoza, un mercader arrepentido, en busca de redención que, fascinado por la labor del padre Gabriel, se ordena sacerdote. La presión llevada a cabo por Portugal obliga a la Iglesia a ceder las tierras en las que se halla la misión.</info>
	</item>
